<?xml version="1.0" encoding="UTF-8"?>
<document id="28545977">
	<sentence id="s1" text="Glutaric aciduria cardiac muscle tissue development I (regulation of apoptotic process-I) is a rare organic aciduria caused by the autosomal recessive inherited deficiency of glutaryl-CoA dehydrogenase (fatty acid beta-oxidation using acyl-CoA dehydrogenase).">
		<entity id="s1.e1" charOffset="18-51"
			type="GO" text="cardiac muscle tissue development" ontology_id="GO_0048738"/>
		<entity id="s1.e2" charOffset="55-86"
			type="GO" text="regulation of apoptotic process" ontology_id="GO_0042981"/>
		<entity id="s1.e3" charOffset="71-87"
			type="HP" text="organic aciduria" ontology_id="HP_0001992"/>
		<entity id="s1.e4" charOffset="102-121"
			type="HP" text="autosomal recessive" ontology_id="HP_0000007"/>
		<entity id="s1.e5" charOffset="174-228"
			type="GO" text="fatty acid beta-oxidation using acyl-CoA dehydrogenase" ontology_id="GO_0033539"/>
		<pair id="s1.p1" e1="s1.e1"
		    e2="s1.e3" pgr="false"/>
		<pair id="s1.p2" e1="s1.e3"
		    e2="s1.e5" pgr="true"/>
		<pair id="s1.p3" e1="s1.e2"
		    e2="s1.e3" pgr="false"/>
		<pair id="s1.p4" e1="s1.e1"
		    e2="s1.e4" pgr="true"/>
		<pair id="s1.p5" e1="s1.e8"
		    e2="s1.e2" pgr="true"/>
		<pair id="s1.p6" e1="s1.e4"
		    e2="s1.e8" pgr="false"/>
	</sentence>
</document>
