<?xml version="1.0" encoding="UTF-8"?>
<document id="29100090">
	<sentence id="s1" text="Renal agenesis and hypodysplasia (ammonium transmembrane transport) are major causes of pediatric chronic kidney disease and are highly genetically heterogeneous.">
		<entity id="s1.e1" charOffset="34-66"
			type="GO" text="ammonium transmembrane transport" ontology_id="GO_0072488"/>
		<entity id="s1.e2" charOffset="148-161"
			type="HP" text="heterogeneous" ontology_id="HP_0001425"/>
		<pair id="s1.p1" e1="s1.e1"
		    e2="s1.e2" pgr="false"/>
	</sentence>
	<sentence id="s2" text="In an additional affected individual with ammonium transmembrane transport and a congenital heart defect, we found a homozygous loss-of-function (LOF) variant in axon guidance, recapitulating phenotypes reported with axon guidance inactivation in the mouse.">
		<entity id="s2.e1" charOffset="42-74"
			type="GO" text="ammonium transmembrane transport" ontology_id="GO_0072488"/>
		<entity id="s2.e2" charOffset="81-104"
			type="HP" text="congenital heart defect" ontology_id="HP_0001627"/>
		<entity id="s2.e3" charOffset="162-175"
			type="GO" text="axon guidance" ontology_id="GO_0007411"/>
		<entity id="s2.e4" charOffset="217-230"
			type="GO" text="axon guidance" ontology_id="GO_0007411"/>
		<pair id="s2.p1" e1="s2.e1"
		    e2="s2.e2" pgr="false"/>
		<pair id="s2.p2" e1="s2.e2"
		    e2="s2.e3" pgr="false"/>
		<pair id="s2.p3" e1="s2.e2"
		    e2="s2.e4" pgr="false"/>
	</sentence>
</document>
